untext/__main__.py
untext/main.py
untext/webview_test.py
untext/css/components.css
untext/css/style.css
untext/css/syntax.css
untext/js/.gitkeep
untext/js/components.js
untext/rendering/dynamic/__init__.py
untext/rendering/dynamic/dom.py
untext/rendering/dynamic/expression.py
untext/rendering/dynamic/statement.py
untext/rendering/static/__init__.py
untext/rendering/static/expression.py
untext/rendering/static/html.py
untext/rendering/static/statement.py
untext-0.0.9.dist-info/METADATA
untext-0.0.9.dist-info/WHEEL
untext-0.0.9.dist-info/entry_points.txt
untext-0.0.9.dist-info/RECORD
