Metadata-Version: 2.4
Name: untext
Version: 0.0.9
Summary: a textless Python IDE, that operates at the AST level
Project-URL: Homepage, https://github.com/lispydev/untext
Author-email: Yacine Cheikhrouhou <yacine.cheikhrouhou@yahoo.fr>
License-Expression: Apache-2.0
Classifier: Intended Audience :: Developers
Classifier: License :: OSI Approved :: Apache Software License
Classifier: Operating System :: OS Independent
Classifier: Programming Language :: Python :: 3
Classifier: Programming Language :: Python :: Implementation :: PyPy
Classifier: Topic :: Text Editors :: Integrated Development Environments (IDE)
Requires-Python: >=3.11
Requires-Dist: pywebview>=5.0.5
